colab_filtering/__init__.py
colab_filtering/norm/__init__.py
colab_filtering/norm/mean.py
colab_filtering/similarity/__init__.py
colab_filtering/similarity/cosine.py
colab_filtering/similarity/jaccard.py
colab_filtering-0.1.2.dist-info/METADATA
colab_filtering-0.1.2.dist-info/WHEEL
colab_filtering-0.1.2.dist-info/licenses/LICENSE.txt
colab_filtering-0.1.2.dist-info/RECORD
