Metadata-Version: 2.4
Name: colab-filtering
Version: 0.1.2
Summary: Simple package for colaborative filtering
Author: Henning Schmies
Author-email: henning.schmies@stud.th-deg.de
License: MIT License
License-File: LICENSE.txt
Keywords: big data,colaborative filtering,filtering,recommendation
Classifier: Development Status :: 4 - Beta
Classifier: Programming Language :: Python
Requires-Python: >=3.12
Requires-Dist: pandas<2.3,>=2.2.0
